scripts/__init__.py
scripts/nautilus_gui.py
scripts/organise.py
Organise-2.0.0.dist-info/METADATA
Organise-2.0.0.dist-info/WHEEL
Organise-2.0.0.dist-info/entry_points.txt
Organise-2.0.0.dist-info/top_level.txt
Organise-2.0.0.dist-info/RECORD
