Metadata-Version: 2.1
Name: Organise
Version: 2.0.0
Summary: A little tool that helps you organise your directory into meaningful subdirectories.
Home-page: https://github.com/mayankkushal/auto-organise
Author: Mayank Kushal
Author-email: mayankkushal26@gmail.com
License: Creative Commons Attribution-Noncommercial-Share Alike license
Platform: UNKNOWN
Requires-Dist: Click
Requires-Dist: tqdm
